omu_meteorology/__init__.py
omu_meteorology/eddydata_preprocessor.py
omu_meteorology/fft_file_reorganizer.py
omu_meteorology/flux_footprint_analyzer.py
omu_meteorology/spectrum_calculator.py
omu_meteorology/transfer_function_calculator.py
omu_meteorology-0.1.3.dist-info/METADATA
omu_meteorology-0.1.3.dist-info/WHEEL
omu_meteorology-0.1.3.dist-info/licenses/LICENSE
omu_meteorology-0.1.3.dist-info/RECORD
