Metadata-Version: 2.3
Name: omu-meteorology
Version: 0.1.3
Summary: 大阪公立大学生態気象学研究グループのパッケージ
Project-URL: Homepage, https://github.com/connect0459/omu-meteorology
Project-URL: Bug Tracker, https://github.com/connect0459/omu-meteorology/issues
Author-email: connect0459 <connect0459@gmail.com>
License-Expression: MIT
License-File: LICENSE
Keywords: meteorology,omu
Classifier: Development Status :: 3 - Alpha
Classifier: Intended Audience :: Science/Research
Classifier: License :: OSI Approved :: MIT License
Classifier: Programming Language :: Python :: 3
Classifier: Programming Language :: Python :: 3.11
Classifier: Topic :: Scientific/Engineering :: Atmospheric Science
Requires-Python: >=3.11
Requires-Dist: jpholiday
Requires-Dist: matplotlib
Requires-Dist: numpy
Requires-Dist: pandas
Requires-Dist: pillow
Requires-Dist: scipy
Requires-Dist: tqdm
